MANIFEST.in
README.rst
setup.py
alipay/__init__.py
alipay/admin.py
alipay/alipay.py
alipay/apps.py
alipay/helpers.py
alipay/models.py
alipay/signals.py
alipay/urls.py
alipay/views.py
alipay/migrations/0001_initial.py
alipay/migrations/0002_auto_20170808_0510.py
alipay/migrations/0003_alipaypayment_user.py
alipay/migrations/0004_auto_20180111_0941.py
alipay/migrations/0005_auto_20180331_0936.py
alipay/migrations/0006_alipaypayment_buyer_id.py
alipay/migrations/0007_auto_20180719_1033.py
alipay/migrations/0008_fix_must_pay_before_20180718_0841.py
alipay/migrations/0009_refund.py
alipay/migrations/0010_alipaypayment_refund_total.py
alipay/migrations/0011_migrate_provider.py
alipay/migrations/__init__.py
alipay/templates/alipay/return.html
alipay/tests/__init__.py
alipay/tests/test_models.py
alipay/tests/test_views.py
django_alipay2/__init__.py
django_alipay2/settings.py
django_alipay2/urls.py
django_alipay2/wsgi.py
django_alipay2.egg-info/PKG-INFO
django_alipay2.egg-info/SOURCES.txt
django_alipay2.egg-info/dependency_links.txt
django_alipay2.egg-info/requires.txt
django_alipay2.egg-info/top_level.txt
sample/__init__.py
sample/admin.py
sample/apps.py
sample/urls.py
sample/views.py